metaregistry/version.py
metaregistry/__init__.py
metaregistry/api.py
metaregistry/cli.py
metaregistry/py.typed
metaregistry/__main__.py
metaregistry-0.0.1.dist-info/licenses/LICENSE
metaregistry-0.0.1.dist-info/WHEEL
metaregistry-0.0.1.dist-info/entry_points.txt
metaregistry-0.0.1.dist-info/METADATA
metaregistry-0.0.1.dist-info/RECORD
